security_use/__init__.py
security_use/cli.py
security_use/dependency_scanner.py
security_use/iac_scanner.py
security_use/models.py
security_use/osv_client.py
security_use/py.typed
security_use/reporter.py
security_use/scanner.py
security_use/auth/__init__.py
security_use/auth/client.py
security_use/auth/config.py
security_use/auth/oauth.py
security_use/compliance/__init__.py
security_use/compliance/mapper.py
security_use/compliance/models.py
security_use/fixers/__init__.py
security_use/fixers/dependency_fixer.py
security_use/fixers/iac_fixer.py
security_use/iac/__init__.py
security_use/iac/base.py
security_use/iac/cloudformation.py
security_use/iac/terraform.py
security_use/iac/rules/__init__.py
security_use/iac/rules/aws.py
security_use/iac/rules/azure.py
security_use/iac/rules/base.py
security_use/iac/rules/gcp.py
security_use/iac/rules/kubernetes.py
security_use/iac/rules/registry.py
security_use/parsers/__init__.py
security_use/parsers/base.py
security_use/parsers/composer.py
security_use/parsers/conda.py
security_use/parsers/dotnet.py
security_use/parsers/gradle.py
security_use/parsers/maven.py
security_use/parsers/npm.py
security_use/parsers/pipfile.py
security_use/parsers/poetry_lock.py
security_use/parsers/pyproject.py
security_use/parsers/requirements.py
security_use/parsers/yarn.py
security_use/sbom/__init__.py
security_use/sbom/generator.py
security_use/sbom/models.py
security_use/sensor/__init__.py
security_use/sensor/config.py
security_use/sensor/dashboard_alerter.py
security_use/sensor/detector.py
security_use/sensor/endpoint_analyzer.py
security_use/sensor/middleware.py
security_use/sensor/models.py
security_use/sensor/webhook.py
security_use-0.2.8.dist-info/METADATA
security_use-0.2.8.dist-info/WHEEL
security_use-0.2.8.dist-info/entry_points.txt
security_use-0.2.8.dist-info/licenses/LICENSE
security_use-0.2.8.dist-info/RECORD
