Metadata-Version: 2.4
Name: security-use
Version: 0.2.8
Summary: Security scanning tool for dependencies and Infrastructure as Code
Project-URL: Homepage, https://github.com/security-use/security-use
Project-URL: Repository, https://github.com/security-use/security-use
Project-URL: Issues, https://github.com/security-use/security-use/issues
Author-email: Security Use <security@example.com>
License-Expression: MIT
License-File: LICENSE
Keywords: cloudformation,dependencies,iac,scanner,security,terraform,vulnerability
Classifier: Development Status :: 3 - Alpha
Classifier: Environment :: Console
Classifier: Intended Audience :: Developers
Classifier: License :: OSI Approved :: MIT License
Classifier: Operating System :: OS Independent
Classifier: Programming Language :: Python :: 3
Classifier: Programming Language :: Python :: 3.10
Classifier: Programming Language :: Python :: 3.11
Classifier: Programming Language :: Python :: 3.12
Classifier: Topic :: Security
Classifier: Topic :: Software Development :: Quality Assurance
Requires-Python: >=3.10
Requires-Dist: click>=8.0.0
Requires-Dist: httpx>=0.25.0
Requires-Dist: packaging>=23.0
Requires-Dist: python-hcl2>=4.3.0
Requires-Dist: pyyaml>=6.0
Requires-Dist: rich>=13.0.0
Requires-Dist: tomli>=2.0.0; python_version < '3.11'
Provides-Extra: dev
Requires-Dist: mypy>=1.0.0; extra == 'dev'
Requires-Dist: pytest-asyncio>=0.21.0; extra == 'dev'
Requires-Dist: pytest>=7.0.0; extra == 'dev'
Requires-Dist: ruff>=0.1.0; extra == 'dev'
Requires-Dist: types-pyyaml>=6.0.0; extra == 'dev'
Provides-Extra: sensor
Requires-Dist: fastapi>=0.100.0; extra == 'sensor'
Requires-Dist: flask>=2.0.0; extra == 'sensor'
